uht_discovery/__init__.py
uht_discovery/cli.py
uht_discovery/gui.py
uht_discovery/core/BLASTer.py
uht_discovery/core/ESM2_scoring_method_testing.py
uht_discovery/core/__init__.py
uht_discovery/core/biophysical_signals_analysis.py
uht_discovery/core/common.py
uht_discovery/core/comprehensive_benchmarking_pipeline.py
uht_discovery/core/config.py
uht_discovery/core/kmeansbenchmark.py
uht_discovery/core/kmeansbenchmark_controls.py
uht_discovery/core/mutation_tester.py
uht_discovery/core/optimizer.py
uht_discovery/core/phylogenetic_analysis.py
uht_discovery/core/plmclust.py
uht_discovery/core/plmclustv2.py
uht_discovery/core/port.py
uht_discovery/core/sequence_similarity_analysis.py
uht_discovery/core/trim.py
uht_discovery/core/tsne_visualization.py
uht_discovery-0.1.2.dist-info/licenses/LICENSE
uht_discovery-0.1.2.dist-info/METADATA
uht_discovery-0.1.2.dist-info/WHEEL
uht_discovery-0.1.2.dist-info/entry_points.txt
uht_discovery-0.1.2.dist-info/top_level.txt
uht_discovery-0.1.2.dist-info/RECORD
