Metadata-Version: 2.4
Name: uht-discovery
Version: 0.1.2
Summary: Semi-automated protein discovery pipeline using BLAST, quality control, and language model clustering
Home-page: https://github.com/Matt115A/uht-discovery
Author: Matthew Penner
Author-email: mp957@cam.ac.uk
Project-URL: Bug Reports, https://github.com/Matt115A/uht-discovery/issues
Project-URL: Source, https://github.com/Matt115A/uht-discovery
Project-URL: Documentation, https://github.com/Matt115A/uht-discovery#readme
Keywords: bioinformatics protein discovery BLAST clustering language models ESM2
Classifier: Development Status :: 3 - Alpha
Classifier: Intended Audience :: Science/Research
Classifier: Topic :: Scientific/Engineering :: Bio-Informatics
Classifier: License :: OSI Approved :: MIT License
Classifier: Programming Language :: Python :: 3
Classifier: Programming Language :: Python :: 3.10
Requires-Python: ~=3.10.0
License-File: LICENSE
Requires-Dist: numpy<3.0.0,>=2.0.0
Requires-Dist: pandas<3.0.0,>=2.0.0
Requires-Dist: scipy<2.0.0,>=1.11.0
Requires-Dist: scikit-learn<2.0.0,>=1.3.0
Requires-Dist: pyyaml<7.0.0,>=6.0.0
Requires-Dist: tqdm<5.0.0,>=4.67.0
Requires-Dist: biopython<2.0.0,>=1.85
Requires-Dist: pysam<1.0.0,>=0.23.0
Requires-Dist: torch<3.0.0,>=2.0.0
Requires-Dist: fair-esm<3.0.0,>=2.0.0
Requires-Dist: matplotlib<4.0.0,>=3.10.0
Requires-Dist: seaborn<1.0.0,>=0.13.0
Requires-Dist: plotly<7.0.0,>=6.2.0
Requires-Dist: gradio<6.0.0,>=5.49.0
Requires-Dist: umap-learn<1.0.0,>=0.5.9
Requires-Dist: statsmodels<1.0.0,>=0.14.0
Requires-Dist: threadpoolctl<4.0.0,>=3.6.0
Dynamic: author
Dynamic: author-email
Dynamic: classifier
Dynamic: description
Dynamic: description-content-type
Dynamic: home-page
Dynamic: keywords
Dynamic: license-file
Dynamic: project-url
Dynamic: requires-dist
Dynamic: requires-python
Dynamic: summary
